python_cloudflare_stream/__init__.py
python_cloudflare_stream/client.py
python_cloudflare_stream-0.1.0.dist-info/WHEEL
python_cloudflare_stream-0.1.0.dist-info/METADATA
python_cloudflare_stream-0.1.0.dist-info/RECORD
