Metadata-Version: 2.1
Name: python-cloudflare-stream
Version: 0.1.0
Summary: A Python wrapper for Cloudflare Stream's API
Home-page: https://github.com/arbington/python-cloudflare-stream
Keywords: vimeo,python,api
Author: Kalob Taulien
Author-email: kalob.taulien@gmail.com
Requires-Python: >=3.9,<4.0
Classifier: Environment :: Web Environment
Classifier: Intended Audience :: Developers
Classifier: License :: OSI Approved :: BSD License
Classifier: Operating System :: OS Independent
Classifier: Programming Language :: Python
Classifier: Programming Language :: Python :: 3
Classifier: Programming Language :: Python :: 3.10
Classifier: Programming Language :: Python :: 3.9
Requires-Dist: requests (>=2.27.1,<3.0.0)
Project-URL: Repository, https://github.com/arbington/python-cloudflare-stream
